retexto/__init__.py
retexto/retexto.py
retexto/stopwords.py
retexto/unicodes_codes.py
retexto/__pycache__/__init__.cpython-38.pyc
retexto/__pycache__/retexto.cpython-38.pyc
retexto/__pycache__/stopwords.cpython-38.pyc
retexto/__pycache__/unicodes_codes.cpython-38.pyc
retexto-1.6.1.dist-info/LICENSE
retexto-1.6.1.dist-info/METADATA
retexto-1.6.1.dist-info/WHEEL
retexto-1.6.1.dist-info/top_level.txt
retexto-1.6.1.dist-info/RECORD
