Metadata-Version: 2.1
Name: retexto
Version: 1.6.1
Summary: Fast text processing
Home-page: https://github.com/Edux87/retexto
Author: Edgar Castañeda
Author-email: edaniel15@gmail.com
License: UNKNOWN
Platform: linux
Platform: windows
Classifier: Development Status :: 5 - Production/Stable
Classifier: Intended Audience :: Developers
Classifier: Programming Language :: Python
Classifier: Programming Language :: Python :: 2.6
Classifier: Programming Language :: Python :: 2.7
Classifier: Programming Language :: Python :: 3
Classifier: Environment :: Console
Classifier: Operating System :: OS Independent
Classifier: License :: OSI Approved :: Apache Software License
Classifier: Topic :: Text Editors :: Text Processing
Classifier: Topic :: Text Editors :: Word Processors
Requires-Dist: unidecode
